__init__.py
jarnsaxa.py
jarnsaxa-0.0.0.dist-info/LICENSE
jarnsaxa-0.0.0.dist-info/METADATA
jarnsaxa-0.0.0.dist-info/WHEEL
jarnsaxa-0.0.0.dist-info/top_level.txt
jarnsaxa-0.0.0.dist-info/RECORD
